[
  {
    "id": 1,
    "type": "series",
    "title": "Stranger Things",
    "rating": 1,
    "cover_img": "assets/images/series/Stranger Things.png",
    "consumed_date": "2022-10-10",
    "seasons_watched": 4,
    "seasons_total": 5,
    "use_episodes": false,
    "episodes_watched": null,
    "episodes_total": null
  },
  {
    "id": 2,
    "type": "games",
    "title": "Elden Ring",
    "rating": 2,
    "cover_img": "assets/images/games/Elden Ring.jpg",
    "consumed_date": "2023-03-15",
    "hours_played": 113,
    "online": false,
    "beaten": true,
    "trophies_total": 42,
    "trophies_obtained": 42
  },
  {
    "id": 3,
    "type": "books",
    "title": "The Novice: Summoner",
    "rating": 3,
    "cover_img": "assets/images/books/Summoner The Novice.jpg",
    "consumed_date": "2018-08-30",
    "pages_read": 384,
    "pages_total": 384
  },
  {
    "id": 4,
    "type": "animated_movies",
    "title": "Justice League: Flashpoint Paradox",
    "rating": 1,
    "cover_img": "assets/images/animated_movies/Justice League Flashpoint Paradox.jpg",
    "consumed_date": "2015-10-13",
    "duration_only_minutes": 97,
    "use_hours": false,
    "duration_hours": null,
    "duration_minutes": null
  },
  {
    "id": 5,
    "type": "movies",
    "title": "Interstellar",
    "rating": 4,
    "cover_img": "assets/images/movies/Interstellar.png",
    "consumed_date": "2017-10-13",
    "duration_only_minutes": null,
    "use_hours": true,
    "duration_hours": 2,
    "duration_minutes": 35
  },
  {
    "id": 6,
    "type": "mangas",
    "title": "Berserk",
    "rating": 5,
    "cover_img": "assets/images/manga/Berserk.jpg",
    "consumed_date": "2024-10-13",
    "volume_amount": 42,
    "volume_read": 21
  },
  {
    "id": 7,
    "type": "animations",
    "title": "Cyberpunk: Edgerunners",
    "rating": 5.5,
    "cover_img": "assets/images/animations/Cyberpunk Edgeruners.jpg",
    "consumed_date": "2025-10-13",
    "seasons_watched": null,
    "seasons_total": null,
    "use_episodes": true,
    "episodes_watched": 12,
    "episodes_total": 12
  },
  {
    "id": 8,
    "type": "games",
    "title": "Elden Ring Nightreign",
    "rating": 6,
    "cover_img": "assets/images/games/Elden Ring Nightreign.jfif",
    "consumed_date": "2025-06-02",
    "hours_played": 17,
    "online": true,
    "beaten": false,
    "trophies_total": 37,
    "trophies_obtained": 37
  },
  {
    "id": 10,
    "type": "games",
    "title": "Multiversus",
    "rating": 7,
    "cover_img": "assets/images/games/Multiversus.jpg",
    "consumed_date": "2022-04-26",
    "hours_played": 30,
    "online": true,
    "beaten": false,
    "trophies_total": 28,
    "trophies_obtained": 2
  },
  {
    "id": 9,
    "type": "games",
    "title": "Outer Wilds",
    "rating": 8.4,
    "cover_img": "assets/images/animations/Cyberpunk Edgeruners.jpg",
    "consumed_date": "2021-04-26",
    "hours_played": 29,
    "online": false,
    "beaten": false,
    "trophies_total": 28,
    "trophies_obtained": 27
  },
  {
    "id": 11,
    "type": "comics",
    "title": "Batman: The Killing Joke",
    "rating": 9,
    "cover_img": "assets/images/animated_movies/Batman The Killing Joke.jpg",
    "consumed_date": "2019-04-26",
    "volume_amount": 1,
    "volume_read": 1
  },
  {
    "id": 12,
    "type": "games",
    "title": "Marvel Rivals",
    "rating": 9.5,
    "cover_img": "./assets/images/games/Marvel Rivals.jpg",
    "consumed_date": "2025-06-18",
    "hours_played": 331,
    "online": true,
    "beaten": false,
    "trophies_total": 99,
    "trophies_obtained": 97
  },
  {
    "id": 13,
    "type": "games",
    "title": "9 Kings",
    "rating": 10,
    "cover_img": "./assets/images/games/9 Kings.jpg",
    "consumed_date": "2025-06-18",
    "hours_played": 13.1,
    "online": false,
    "beaten": true,
    "trophies_total": 28,
    "trophies_obtained": 28
  },
  {
    "id": 14,
    "type": "books",
    "title": "Lord of the Rings",
    "rating": 10,
    "cover_img": "assets/images/books/LOTR.jpg",
    "consumed_date": "2025-08-30",
    "pages_read": 450,
    "pages_total": 512
  },
  {
    "id": 15,
    "type": "games",
    "title": "Sea of Stars",
    "rating": 10,
    "cover_img": "./assets/images/games/seaofstarts.jpg",
    "consumed_date": "2025-07-16",
    "hours_played": 30.5,
    "online": false,
    "beaten": true,
    "trophies_total": 54,
    "trophies_obtained": 34
  },
  {
    "id": 16,
    "type": "animations",
    "title": "Dragon Ball",
    "rating": 10,
    "cover_img": "./assets/images/animations/dragonball.jpg",
    "consumed_date": "2005-07-16",
    "seasons_watched": null,
    "seasons_total": null,
    "use_episodes": true,
    "episodes_watched": 90,
    "episodes_total": 90
  },
  {
    "id": 17,
    "type": "animations",
    "title": "Dragon Ball Z",
    "rating": 10,
    "cover_img": "./assets/images/animations/dragonballz.jpg",
    "consumed_date": "2010-07-16",
    "seasons_watched": null,
    "seasons_total": null,
    "use_episodes": true,
    "episodes_watched": 310,
    "episodes_total": 310
  },
  {
    "id": 18,
    "type": "animations",
    "title": "Dragon Ball Super",
    "rating": 10,
    "cover_img": "./assets/images/animations/dragonballsuper.jpg",
    "consumed_date": "2017-07-16",
    "seasons_watched": null,
    "seasons_total": null,
    "use_episodes": true,
    "episodes_watched": 250,
    "episodes_total": 250
  },
  {
    "id": 19,
    "type": "books",
    "title": "The Novice: 2",
    "rating": 9.5,
    "cover_img": "./assets/images/books/summoner.jpg",
    "consumed_date": "2018-08-30",
    "pages_read": 384,
    "pages_total": 384
  },
  {
    "id": 20,
    "type": "books",
    "title": "The Novice: 3",
    "rating": 7,
    "cover_img": "./assets/images/books/summoner3.jpg",
    "consumed_date": "2011-08-30",
    "pages_read": 384,
    "pages_total": 385
  },
  {
    "id": 21,
    "type": "books",
    "title": "Lord of the Rings 2",
    "rating": 7,
    "cover_img": "./assets/images/books/lord2.jpg",
    "consumed_date": "2019-08-30",
    "pages_read": 384,
    "pages_total": 550
  },
  {
    "id": 22,
    "type": "series",
    "title": "Breaking Bad",
    "rating": 10,
    "cover_img": "assets/images/series/breakingBad.jpg",
    "consumed_date": "2021-10-10",
    "seasons_watched": 5,
    "seasons_total": 5,
    "use_episodes": false,
    "episodes_watched": null,
    "episodes_total": null
  },
  {
    "id": 23,
    "type": "animations",
    "title": "One Piece",
    "rating": 9.5,
    "cover_img": "assets/images/animations/onepiece.jpg",
    "consumed_date": "2023-10-15",
    "seasons_watched": null,
    "seasons_total": null,
    "use_episodes": true,
    "episodes_watched": 1112,
    "episodes_total": 1250
  },
  {
    "id": 24,
    "type": "series",
    "title": "The Boys",
    "rating": 9,
    "cover_img": "assets/images/series/theBoys.jpg",
    "consumed_date": "2024-10-10",
    "seasons_watched": 4,
    "seasons_total": 5,
    "use_episodes": false,
    "episodes_watched": null,
    "episodes_total": null
  },
  {
    "id": 25,
    "type": "animated_movies",
    "title": "Toy Story",
    "rating": 6,
    "cover_img": "assets/images/animated_movies/toyStory.jpg",
    "consumed_date": "2021-10-13",
    "duration_only_minutes": 95,
    "use_hours": false,
    "duration_hours": null,
    "duration_minutes": null
  },
  {
    "id": 26,
    "type": "games",
    "title": "Dave the Diver",
    "rating": 8.5,
    "cover_img": "assets/images/games/davethediver.jpg",
    "consumed_date": "2024-03-15",
    "hours_played": 30,
    "online": false,
    "beaten": true,
    "trophies_total": 39,
    "trophies_obtained": 39
  }
]